maligner/__init__.py
maligner/__main__.py
maligner/aligner.py
maligner/icons.py
maligner/mainwindow.py
maligner/mtypes.py
maligner/pixmaps/Change_E_Z.png
maligner/pixmaps/Change_E_Z.svg
maligner/pixmaps/Change_R_S.png
maligner/pixmaps/MCS.png
maligner/pixmaps/about.png
maligner/pixmaps/appicon.png
maligner/pixmaps/appicon.svg.png
maligner/pixmaps/calc.png
maligner/pixmaps/exit.png
maligner/pixmaps/grid.png
maligner/pixmaps/icons8-Anchor.png
maligner/pixmaps/icons8-Broom.png
maligner/pixmaps/icons8-Bulleted List.png
maligner/pixmaps/icons8-Cancel.png
maligner/pixmaps/icons8-Carbon.png
maligner/pixmaps/icons8-Cursor.png
maligner/pixmaps/icons8-Decrease Font.png
maligner/pixmaps/icons8-Delete.png
maligner/pixmaps/icons8-Double.png
maligner/pixmaps/icons8-Edit.png
maligner/pixmaps/icons8-Exit.png
maligner/pixmaps/icons8-Hydrogen.png
maligner/pixmaps/icons8-Increase Font.png
maligner/pixmaps/icons8-Info.png
maligner/pixmaps/icons8-Left.png
maligner/pixmaps/icons8-Line.png
maligner/pixmaps/icons8-Minus.png
maligner/pixmaps/icons8-Molecule.png
maligner/pixmaps/icons8-Open.png
maligner/pixmaps/icons8-Oxygen.png
maligner/pixmaps/icons8-Physics.png
maligner/pixmaps/icons8-Pinch.png
maligner/pixmaps/icons8-Plus.png
maligner/pixmaps/icons8-Redo.png
maligner/pixmaps/icons8-Replace Atom.png
maligner/pixmaps/icons8-Reset.png
maligner/pixmaps/icons8-Right.png
maligner/pixmaps/icons8-Save as.png
maligner/pixmaps/icons8-Save.png
maligner/pixmaps/icons8-Scatter Plot.png
maligner/pixmaps/icons8-Shutdown.png
maligner/pixmaps/icons8-Single.png
maligner/pixmaps/icons8-Trash.png
maligner/pixmaps/icons8-Triple.png
maligner/pixmaps/icons8-Undo.png
maligner/pixmaps/molblock.png
maligner/pixmaps/next.png
maligner/pixmaps/open.png
maligner/pixmaps/plot.png
maligner/pixmaps/prev.png
maligner/pixmaps/ptable.png
maligner/pixmaps/ptable.svg
maligner/translations/pt_BR.qm
maligner/translations/pt_BR.ts
maligner/widgets/MolGridView.py
maligner/widgets/molEditWidget.py
maligner-0.0.2.dist-info/METADATA
maligner-0.0.2.dist-info/WHEEL
maligner-0.0.2.dist-info/entry_points.txt
maligner-0.0.2.dist-info/licenses/LICENSE
maligner-0.0.2.dist-info/RECORD
