Metadata-Version: 2.3
Name: maligner
Version: 0.0.2
Summary: An Open-Source Molecular Alignment Tool
Project-URL: Homepage, https://github.com/hellmrf/maligner
Author-email: Heliton Martins <helitonmrf@gmail.com>
License:                     GNU GENERAL PUBLIC LICENSE
Requires-Python: >=3.12
Requires-Dist: datamol>=0.12.5
Requires-Dist: numpy>=2.1.3
Requires-Dist: pandas>=2.2.3
Requires-Dist: pyside6>=6.8.1
Requires-Dist: rdkit>=2024.3.6
